htnhello/__init__.py
htnhello/greet.py
htnhello-1.1.0.dist-info/METADATA
htnhello-1.1.0.dist-info/WHEEL
htnhello-1.1.0.dist-info/entry_points.txt
htnhello-1.1.0.dist-info/top_level.txt
htnhello-1.1.0.dist-info/RECORD
