Metadata-Version: 2.1
Name: htnhello
Version: 1.1.0
Summary: Hello World for Nexus PyPI.
Home-page: https://github.com/kynthus/htnpython
Author: Kynthus Aueoau
License: MIT
Platform: UNKNOWN
Classifier: License :: OSI Approved :: MIT License
Classifier: Programming Language :: Python :: 2
Classifier: Programming Language :: Python :: 2.7
